{
    "cluster": "cruddur",
    "launchType": "FARGATE",
    "desiredCount": 1,
    "enableECSManagedTags": true,
    "enableExecuteCommand": true,
    "networkConfiguration": {
      "awsvpcConfiguration": {
        "assignPublicIp": "ENABLED",
        "securityGroups": [
          "sg-0f3bf8460d8f05dfd"
        ],
        "subnets": [
          "subnet-07926897d9cc9787a",
          "subnet-03393663ad35f93f3",
          "subnet-0abb0bdefcdc6ae07"
        ]
      }
    },
    "serviceConnectConfiguration": {
      "enabled": true,
      "namespace": "cruddur",
      "services": [
        {
          "portName": "backend-flask",
          "discoveryName": "backend-flask",
          "clientAliases": [{"port": 4567}]
        }
      ]
    },
    "propagateTags": "SERVICE",
    "serviceName": "backend-flask",
    "taskDefinition": "backend-flask"
  }
